pydobot/__init__.py
pydobot/dobot.py
pydobot/message.py
pydobot/enums/CommunicationProtocolIDs.py
pydobot/enums/ControlValues.py
pydobot/enums/__init__.py
pydobot/enums/ptpMode.py
pydobot-1.3.2.dist-info/LICENSE.txt
pydobot-1.3.2.dist-info/METADATA
pydobot-1.3.2.dist-info/WHEEL
pydobot-1.3.2.dist-info/top_level.txt
pydobot-1.3.2.dist-info/RECORD
