Metadata-Version: 2.1
Name: pydobot
Version: 1.3.2
Summary: Python library for Dobot Magician
Home-page: https://github.com/luismesas/pydobot
Author: Luis Mesas
Author-email: luismesas@gmail.com
License: UNKNOWN
Download-URL: https://github.com/luismesas/pydobot/archive/v1.2.0.tar.gz
Keywords: dobot,magician,robotics
Platform: UNKNOWN
